setup.py
ourse/__init__.py
ourse/database.py
ourse/dataserver.py
ourse/sparqlserver.py
ourse/storage.py
ourse/translation.py
ourse/driver/ZEODriver.py
ourse/driver/__init__.py
ourse/driver/basic.py
pyOURSE.egg-info/PKG-INFO
pyOURSE.egg-info/SOURCES.txt
pyOURSE.egg-info/dependency_links.txt
pyOURSE.egg-info/requires.txt
pyOURSE.egg-info/top_level.txt
