Metadata-Version: 1.0
Name: pyOURSE
Version: 0.1
Summary: An implementation of the OURSE model for ODBMS->RDF translation, done in Python
Home-page: http://wiki.strigo.eu/OURSE
Author: Pedro Ferreira
Author-email: ilzogoiby@gmail.com
License: GPL
Platform: UNKNOWN
Classifier: Development Status :: 3 - Alpha
Classifier: Framework :: ZODB
Classifier: Intended Audience :: Developers
Classifier: License :: OSI Approved :: GNU General Public License (GPL)
Classifier: Topic :: Database :: Front-Ends
Classifier: Topic :: Internet :: WWW/HTTP
